mcp_cookie_cutter/__init__.py
mcp_cookie_cutter/cli.py
mcp_cookie_cutter/template/cookiecutter.json
mcp_cookie_cutter/template/examples/multi-auth-api.json
mcp_cookie_cutter/template/examples/openweather-api.json
mcp_cookie_cutter/template/examples/petstore-swagger.json
mcp_cookie_cutter/template/examples/thecatapi.yaml
mcp_cookie_cutter/template/hooks/openapi_generator.py
mcp_cookie_cutter/template/hooks/post_gen_project.py
mcp_cookie_cutter/template/hooks/pre_gen_project.py
mcp_cookie_cutter/template/{{cookiecutter.project_slug}}/CUSTOMIZATION.md
mcp_cookie_cutter/template/{{cookiecutter.project_slug}}/Dockerfile
mcp_cookie_cutter/template/{{cookiecutter.project_slug}}/README.md
mcp_cookie_cutter/template/{{cookiecutter.project_slug}}/docker-compose.yml
mcp_cookie_cutter/template/{{cookiecutter.project_slug}}/pyproject.toml
mcp_cookie_cutter/template/{{cookiecutter.project_slug}}/test_server.py
mcp_cookie_cutter/template/{{cookiecutter.project_slug}}/src/{{cookiecutter.project_slug}}/__init__.py
mcp_cookie_cutter/template/{{cookiecutter.project_slug}}/src/{{cookiecutter.project_slug}}/server.py
mcp_cookie_cutter-0.2.0.dist-info/licenses/LICENSE
mcp_cookie_cutter-0.2.0.dist-info/METADATA
mcp_cookie_cutter-0.2.0.dist-info/WHEEL
mcp_cookie_cutter-0.2.0.dist-info/entry_points.txt
mcp_cookie_cutter-0.2.0.dist-info/top_level.txt
mcp_cookie_cutter-0.2.0.dist-info/RECORD
