Metadata-Version: 2.4
Name: mcp-cookie-cutter
Version: 0.2.0
Summary: Intelligent MCP server generator from OpenAPI/Swagger specs
Author: Mahesh Mahadevan
Maintainer: Mahesh Mahadevan
License: MIT
Project-URL: Homepage, https://github.com/maheshmahadevan/mcp-cookie-cutter
Project-URL: Documentation, https://github.com/maheshmahadevan/mcp-cookie-cutter#readme
Project-URL: Repository, https://github.com/maheshmahadevan/mcp-cookie-cutter
Project-URL: Issues, https://github.com/maheshmahadevan/mcp-cookie-cutter/issues
Project-URL: Changelog, https://github.com/maheshmahadevan/mcp-cookie-cutter/blob/main/CHANGELOG.md
Keywords: mcp,model-context-protocol,cookiecutter,template,openapi,swagger,fastmcp,code-generator,scaffolding
Classifier: Development Status :: 4 - Beta
Classifier: Intended Audience :: Developers
Classifier: License :: OSI Approved :: MIT License
Classifier: Operating System :: OS Independent
Classifier: Programming Language :: Python :: 3
Classifier: Programming Language :: Python :: 3.10
Classifier: Programming Language :: Python :: 3.11
Classifier: Programming Language :: Python :: 3.12
Classifier: Programming Language :: Python :: 3.13
Classifier: Topic :: Software Development :: Code Generators
Classifier: Topic :: Software Development :: Libraries :: Python Modules
Classifier: Topic :: Internet :: WWW/HTTP :: HTTP Servers
Classifier: Framework :: FastAPI
Classifier: Typing :: Typed
Requires-Python: >=3.10
License-File: LICENSE
Requires-Dist: cookiecutter>=2.1.0
Requires-Dist: pyyaml>=6.0
Requires-Dist: requests>=2.31.0
Requires-Dist: openapi-pydantic>=0.4.0
Requires-Dist: datamodel-code-generator>=0.25.0
Provides-Extra: dev
Requires-Dist: pytest>=7.0.0; extra == "dev"
Requires-Dist: black>=23.0.0; extra == "dev"
Requires-Dist: ruff>=0.1.0; extra == "dev"
Requires-Dist: mypy>=1.0.0; extra == "dev"
Requires-Dist: build>=1.0.0; extra == "dev"
Requires-Dist: twine>=4.0.0; extra == "dev"
Dynamic: license-file
